{
"type": "FeatureCollection",
"name": "geo_32_介護医療院",
"crs": { "type": "name", "properties": { "name": "urn:ogc:def:crs:OGC:1.3:CRS84" } },
"features": [
{ "type": "Feature", "properties": { "内容": "ケアセンター喜南【介護医療院】島根県松江市宍道町白石129-2", "url": "https://www.kaigokensaku.mhlw.go.jp/32/index.php?action_kouhyou_detail_004_kani=true&JigyosyoCd=32B0100055-00&ServiceCd=550&Type=search", "url2": "https://www.doujinkai.jp/kinan/" }, "geometry": { "type": "Point", "coordinates": [ 132.925920100000013, 35.4141227 ] } },
{ "type": "Feature", "properties": { "内容": "介護医療院　虹【介護医療院】島根県松江市佐草町456-1", "url": "https://www.kaigokensaku.mhlw.go.jp/32/index.php?action_kouhyou_detail_004_kani=true&JigyosyoCd=32B0100048-00&ServiceCd=550&Type=search", "url2": "https://www.mhs-niji.jp/" }, "geometry": { "type": "Point", "coordinates": [ 133.072085, 35.4317278 ] } },
{ "type": "Feature", "properties": { "内容": "医療法人社団創健会　介護医療院宇賀の里つばさ【介護医療院】島根県松江市上乃木三丁目４番１号", "url": "https://www.kaigokensaku.mhlw.go.jp/32/index.php?action_kouhyou_detail_004_kani=true&JigyosyoCd=32B0100030-00&ServiceCd=550&Type=search", "url2": "https://www.souken-kai.or.jp/" }, "geometry": { "type": "Point", "coordinates": [ 133.0589539, 35.4485118 ] } },
{ "type": "Feature", "properties": { "内容": "殿町介護医療院【介護医療院】島根県浜田市殿町83番地31", "url": "https://www.kaigokensaku.mhlw.go.jp/32/index.php?action_kouhyou_detail_004_kani=true&JigyosyoCd=32B0700011-00&ServiceCd=550&Type=search", "url2": null }, "geometry": { "type": "Point", "coordinates": [ 132.0782762, 34.8988754 ] } },
{ "type": "Feature", "properties": { "内容": "介護医療院ひまわり【介護医療院】出雲市神西沖町2479-6", "url": "https://www.kaigokensaku.mhlw.go.jp/32/index.php?action_kouhyou_detail_004_kani=true&JigyosyoCd=32B0400018-00&ServiceCd=550&Type=search", "url2": "https://www.w-himawari.jp/nursing" }, "geometry": { "type": "Point", "coordinates": [ 132.6812932, 35.3370501 ] } },
{ "type": "Feature", "properties": { "内容": "益田市医師会介護医療院ふたば【介護医療院】遠田町1917番地2", "url": "https://www.kaigokensaku.mhlw.go.jp/32/index.php?action_kouhyou_detail_004_kani=true&JigyosyoCd=32B0800019-00&ServiceCd=550&Type=search", "url2": "https://www.masuda-med.or.jp/kaigoiryou/" }, "geometry": { "type": "Point", "coordinates": [ 131.8669835, 34.6967347 ] } },
{ "type": "Feature", "properties": { "内容": "介護医療院　ライトピア【介護医療院】島根県安来市荒島町1817-1", "url": "https://www.kaigokensaku.mhlw.go.jp/32/index.php?action_kouhyou_detail_004_kani=true&JigyosyoCd=32B0200038-00&ServiceCd=550&Type=search", "url2": "https://shirane.clinic/orthopedics/" }, "geometry": { "type": "Point", "coordinates": [ 133.204486699999961, 35.43272910000001 ] } },
{ "type": "Feature", "properties": { "内容": "介護医療院昌寿苑【介護医療院】島根県安来市安来町899-1", "url": "https://www.kaigokensaku.mhlw.go.jp/32/index.php?action_kouhyou_detail_004_kani=true&JigyosyoCd=32B0200012-00&ServiceCd=550&Type=search", "url2": "http://www.syourinkai.or.jp" }, "geometry": { "type": "Point", "coordinates": [ 133.252828521984583, 35.433229750679054 ] } },
{ "type": "Feature", "properties": { "内容": "介護医療院　みずかぜ【介護医療院】島根県安来市伯太町安田1700番地", "url": "https://www.kaigokensaku.mhlw.go.jp/32/index.php?action_kouhyou_detail_004_kani=true&JigyosyoCd=32B0200020-00&ServiceCd=550&Type=search", "url2": null }, "geometry": { "type": "Point", "coordinates": [ 133.273694200000023, 35.3719537 ] } },
{ "type": "Feature", "properties": { "内容": "島根県済生会介護医療院なでしこ江津【介護医療院】島根県江津市江津町1016番地37島根県済生会江津総合病院", "url": "https://www.kaigokensaku.mhlw.go.jp/32/index.php?action_kouhyou_detail_004_kani=true&JigyosyoCd=32B0600013-00&ServiceCd=550&Type=search", "url2": null }, "geometry": { "type": "Point", "coordinates": [ 132.2148922, 35.0123639 ] } },
{ "type": "Feature", "properties": { "内容": "奥出雲病院介護医療院【介護医療院】島根県仁多郡奥出雲町三成１６２２番地１", "url": "https://www.kaigokensaku.mhlw.go.jp/32/index.php?action_kouhyou_detail_004_kani=true&JigyosyoCd=32B1300019-00&ServiceCd=550&Type=search", "url2": "https://www.okuizumo-hospital.jp" }, "geometry": { "type": "Point", "coordinates": [ 132.9971592, 35.1964888 ] } },
{ "type": "Feature", "properties": { "内容": "介護医療院　ケアセンター三笠【介護医療院】島根県邑智郡邑南町上田所39番地5", "url": "https://www.kaigokensaku.mhlw.go.jp/32/index.php?action_kouhyou_detail_004_kani=true&JigyosyoCd=32B1800018-00&ServiceCd=550&Type=search", "url2": "http://tokuyu-kai.sakura.ne.jp" }, "geometry": { "type": "Point", "coordinates": [ 132.5064092, 34.8404591 ] } },
{ "type": "Feature", "properties": { "内容": "よしか介護医療院【介護医療院】島根県鹿足郡吉賀町六日市368番地4", "url": "https://www.kaigokensaku.mhlw.go.jp/32/index.php?action_kouhyou_detail_004_kani=true&JigyosyoCd=32B2100012-00&ServiceCd=550&Type=search", "url2": "https://katakuri.or.jp/" }, "geometry": { "type": "Point", "coordinates": [ 131.937492, 34.353539499999989 ] } }
]
}
