{
"type": "FeatureCollection",
"name": "geo_32_短期入所療養介護（介護医療院）",
"crs": { "type": "name", "properties": { "name": "urn:ogc:def:crs:OGC:1.3:CRS84" } },
"features": [
{ "type": "Feature", "properties": { "内容": "ケアセンター喜南【短期入所療養介護（介護医療院）】島根県松江市宍道町白石129-2", "url": "https://www.kaigokensaku.mhlw.go.jp/32/index.php?action_kouhyou_detail_004_kani=true&JigyosyoCd=32B0100055-00&ServiceCd=551&Type=search", "url2": "https://www.doujinkai.jp/kinan/" }, "geometry": { "type": "Point", "coordinates": [ 132.9259305, 35.4141767 ] } },
{ "type": "Feature", "properties": { "内容": "介護医療院　虹【短期入所療養介護（介護医療院）】島根県松江市佐草町456-1", "url": "https://www.kaigokensaku.mhlw.go.jp/32/index.php?action_kouhyou_detail_004_kani=true&JigyosyoCd=3270104098-00&ServiceCd=551&Type=search", "url2": "https://www.mhs-niji.jp/" }, "geometry": { "type": "Point", "coordinates": [ 133.072085, 35.4317278 ] } },
{ "type": "Feature", "properties": { "内容": "殿町介護医療院【短期入所療養介護（介護医療院）】島根県浜田市殿町83番地31", "url": "https://www.kaigokensaku.mhlw.go.jp/32/index.php?action_kouhyou_detail_004_kani=true&JigyosyoCd=32B0700011-00&ServiceCd=551&Type=search", "url2": null }, "geometry": { "type": "Point", "coordinates": [ 132.0782762, 34.8988754 ] } },
{ "type": "Feature", "properties": { "内容": "介護医療院ひまわり【短期入所療養介護（介護医療院）】島根県出雲市神西沖町2479-6", "url": "https://www.kaigokensaku.mhlw.go.jp/32/index.php?action_kouhyou_detail_004_kani=true&JigyosyoCd=32B0400018-00&ServiceCd=551&Type=search", "url2": "https://www.w-himawari.jp/nursing" }, "geometry": { "type": "Point", "coordinates": [ 132.6812932, 35.3370501 ] } },
{ "type": "Feature", "properties": { "内容": "介護医療院　みずかぜ【短期入所療養介護（介護医療院）】島根県安来市伯太町安田1700番地", "url": "https://www.kaigokensaku.mhlw.go.jp/32/index.php?action_kouhyou_detail_004_kani=true&JigyosyoCd=32B0200020-00&ServiceCd=551&Type=search", "url2": null }, "geometry": { "type": "Point", "coordinates": [ 133.2736942, 35.3719537 ] } },
{ "type": "Feature", "properties": { "内容": "介護医療院昌寿苑【短期入所療養介護（介護医療院）】島根県安来市安来町899-1", "url": "https://www.kaigokensaku.mhlw.go.jp/32/index.php?action_kouhyou_detail_004_kani=true&JigyosyoCd=32B0200012-00&ServiceCd=551&Type=search", "url2": "http://www.syourinkai.or.jp" }, "geometry": { "type": "Point", "coordinates": [ 133.252808083524059, 35.43317904842403 ] } },
{ "type": "Feature", "properties": { "内容": "奥出雲病院介護医療院【短期入所療養介護（介護医療院）】島根県仁多郡奥出雲町三成１６２２番地１", "url": "https://www.kaigokensaku.mhlw.go.jp/32/index.php?action_kouhyou_detail_004_kani=true&JigyosyoCd=32B1300019-00&ServiceCd=551&Type=search", "url2": "https://www.okuizumo-hospital.jp" }, "geometry": { "type": "Point", "coordinates": [ 132.99712164907379, 35.196142487252921 ] } },
{ "type": "Feature", "properties": { "内容": "よしか介護医療院【短期入所療養介護（介護医療院）】島根県鹿足郡吉賀町六日市368番地4", "url": "https://www.kaigokensaku.mhlw.go.jp/32/index.php?action_kouhyou_detail_004_kani=true&JigyosyoCd=32B2100012-00&ServiceCd=551&Type=search", "url2": "https://katakuri.or.jp/" }, "geometry": { "type": "Point", "coordinates": [ 131.937492, 34.3535395 ] } }
]
}
